irrexplorer_cli/__init__.py
irrexplorer_cli/helpers.py
irrexplorer_cli/irrexplorer.py
irrexplorer_cli/main.py
irrexplorer_cli/models.py
irrexplorer_cli/py.typed
irrexplorer_cli/queries.py
irrexplorer_cli-0.0.4.dist-info/METADATA
irrexplorer_cli-0.0.4.dist-info/WHEEL
irrexplorer_cli-0.0.4.dist-info/entry_points.txt
irrexplorer_cli-0.0.4.dist-info/licenses/LICENSE
irrexplorer_cli-0.0.4.dist-info/RECORD
