Metadata-Version: 2.4
Name: irrexplorer-cli
Version: 0.0.4
Summary: A command-line interface to query and explore IRR & BGP data from IRRexplorer.net
Author-email: kiraum <tfgoncalves@xpto.it>
License-File: LICENSE
Requires-Python: >=3.13
Requires-Dist: asyncio
Requires-Dist: backoff
Requires-Dist: httpx
Requires-Dist: pydantic
Requires-Dist: rich
Requires-Dist: typer
Provides-Extra: dev
Requires-Dist: black; extra == 'dev'
Requires-Dist: isort; extra == 'dev'
Requires-Dist: mypy; extra == 'dev'
Requires-Dist: pre-commit; extra == 'dev'
Requires-Dist: pylint; extra == 'dev'
Requires-Dist: pytest; extra == 'dev'
Requires-Dist: pytest-asyncio; extra == 'dev'
Requires-Dist: pytest-cov; extra == 'dev'
Requires-Dist: respx; extra == 'dev'
Requires-Dist: ruff; extra == 'dev'
